feishu_sdk/__init__.py
feishu_sdk/base_client.py
feishu_sdk/feishu_client.py
feishu_sdk/feishu_response.py
feishu_sdk/feishu_server.py
feishu_sdk/card/__init__.py
feishu_sdk/card/card.py
feishu_sdk/card/elements.py
feishu_sdk/card/modules.py
feishu_sdk/card/objects.py
feishu_py_sdk-0.0.1.dist-info/LICENSE.txt
feishu_py_sdk-0.0.1.dist-info/METADATA
feishu_py_sdk-0.0.1.dist-info/WHEEL
feishu_py_sdk-0.0.1.dist-info/top_level.txt
feishu_py_sdk-0.0.1.dist-info/RECORD
