Metadata-Version: 2.1
Name: feishu-py-sdk
Version: 0.0.1
Summary: feishu sdk
Home-page: https://github.com/ilpan/feishu-sdk
Author: ilpan
Author-email: pna.dev@outlook.com
License: UNKNOWN
Keywords: feishu sdk client server
Platform: UNKNOWN
Classifier: Development Status :: 3 - Alpha
Classifier: Intended Audience :: Developers
Classifier: Topic :: Software Development :: Libraries
Classifier: License :: OSI Approved :: MIT License
Classifier: Programming Language :: Python :: 3.6
Classifier: Programming Language :: Python :: 3.7
Requires-Python: >=3.6
Requires-Dist: aiohttp (==3.7.3)
Requires-Dist: chardet (==3.0.4)
Requires-Dist: typing-extensions (==3.7.4.3)
Requires-Dist: async-timeout (==3.0.1) ; python_full_version >= "3.5.3"
Requires-Dist: attrs (==20.3.0) ; python_version >= "2.7" and python_version not in "3.0, 3.1, 3.2, 3.3"
Requires-Dist: idna (==2.10) ; python_version >= "2.7" and python_version not in "3.0, 3.1, 3.2, 3.3"
Requires-Dist: multidict (==5.1.0) ; python_version >= "3.6"
Requires-Dist: yarl (==1.6.3) ; python_version >= "3.6"
Provides-Extra: dev
